vault_keyring_client/__init__.py
vault_keyring_client/main.py
vault_keyring_client-0.2.4.dist-info/LICENSE
vault_keyring_client-0.2.4.dist-info/METADATA
vault_keyring_client-0.2.4.dist-info/WHEEL
vault_keyring_client-0.2.4.dist-info/entry_points.txt
vault_keyring_client-0.2.4.dist-info/RECORD
