Metadata-Version: 2.1
Name: vault-keyring-client
Version: 0.2.4
Summary: 
Home-page: https://git@github.com/jakob1379/vault-keyring-client
License: GPL-3.0-or-later
Author: Jakob Guldberg Aaes
Author-email: jakob1379@gmail.com
Requires-Python: >=3.10,<4.0
Classifier: License :: OSI Approved :: GNU General Public License v3 or later (GPLv3+)
Classifier: Programming Language :: Python :: 3
Classifier: Programming Language :: Python :: 3.10
Classifier: Programming Language :: Python :: 3.11
Classifier: Programming Language :: Python :: 3.12
Requires-Dist: ansible (>=9.6.0)
Requires-Dist: keyring (>=25.2.1)
Requires-Dist: typer (>=0.12.3)
Project-URL: Repository, https://git@github.com/jakob1379/vault-keyring-client
